vnstock_mcp/__init__.py
vnstock_mcp/server.py
vnstock_mcp-0.1.4.dist-info/METADATA
vnstock_mcp-0.1.4.dist-info/WHEEL
vnstock_mcp-0.1.4.dist-info/entry_points.txt
vnstock_mcp-0.1.4.dist-info/top_level.txt
vnstock_mcp-0.1.4.dist-info/RECORD
