Metadata-Version: 2.4
Name: vnstock-mcp
Version: 0.1.4
Summary: Vietnamese Stock Market MCP Server - FastMCP 2.0
License-Expression: MIT
Project-URL: Repository, https://github.com/gahoccode/vnstock-mcp
Keywords: vietnam,stock,market,mcp,fastmcp,financial,vnstock
Requires-Python: >=3.10
Requires-Dist: fastmcp>=2.0.0
Requires-Dist: vnstock==3.2.2
Requires-Dist: vnai==2.1.9
Requires-Dist: pyportfolioopt>=1.5.6
Requires-Dist: pandas
Requires-Dist: anthropic>=0.34.0
Requires-Dist: python-dotenv>=1.0.0
Requires-Dist: aiohttp>=3.8.0
